[
    {
        "user_id": 624076054969188363,
        "command_count": 3191,
        "settings": {},
        "on_pinged": {
            "title": "skill issue gang",
            "description": "just get good",
            "color": 255
        },
        "webhooks": {
            "lol": "https://discord.com/api/webhooks/935106709981126676/FpfLiZ0BQDqxc6NlWinMhWBijG_0IWc-LlmLsrUPg7U1g7wHQlicRITty1sNMM0Nr2rd",
            "rules": "https://discord.com/api/webhooks/936182842180894770/W5_gAlJJWSV0Mzd4TaATYyrhi23N0ymClGN7TavIHDvj8hsFAEnWaI_alZLoaeMzYSBB"
        }
    },
    {
        "user_id": 782350976219873302,
        "command_count": 24,
        "settings": {},
        "on_pinged": {
            "title": null,
            "description": null,
            "color": null
        },
        "webhooks": {}
    },
    {
        "user_id": 913618154318618645,
        "command_count": 204,
        "settings": {
            "update_dms": true,
            "on_pinged": true,
            "passive": true
        },
        "on_pinged": {
            "title": "Shut the fuck up",
            "description": "Beat it, you no life scumbag",
            "color": 255
        },
        "webhooks": {}
    },
    {
        "user_id": 842638586879803402,
        "command_count": 3,
        "settings": {},
        "on_pinged": {
            "title": null,
            "description": null,
            "color": null
        },
        "webhooks": {}
    },
    {
        "user_id": 768693329188749344,
        "command_count": 99,
        "settings": {},
        "on_pinged": {
            "title": "no",
            "description": "bitch fuck",
            "color": 65280
        },
        "webhooks": {}
    },
    {
        "user_id": 768693329188749344,
        "command_count": 173,
        "settings": {},
        "on_pinged": {
            "title": "no",
            "description": "bitch fuck",
            "color": 65280
        },
        "webhooks": {}
    },
    {
        "user_id": 516812635233058826,
        "command_count": 59,
        "settings": {},
        "on_pinged": {
            "title": null,
            "description": null,
            "color": null
        },
        "webhooks": {}
    },
    {
        "user_id": 583032764559917057,
        "command_count": 69,
        "settings": {},
        "on_pinged": {
            "title": "If You need Somethin DM Me",
            "description": "God You Are Stupid (Dum Dum)",
            "color": 16711680
        },
        "webhooks": {}
    },
    {
        "user_id": 270904126974590976,
        "command_count": 938,
        "settings": {},
        "on_pinged": {
            "title": null,
            "description": null,
            "color": null
        },
        "webhooks": {}
    },
    {
        "user_id": 897255745769340938,
        "command_count": 4,
        "settings": {},
        "on_pinged": {
            "title": null,
            "description": null,
            "color": null
        },
        "webhooks": {}
    },
    {
        "user_id": 881251029587488799,
        "command_count": 30,
        "settings": {},
        "on_pinged": {
            "title": null,
            "description": null,
            "color": null
        },
        "webhooks": {}
    },
    {
        "user_id": 850443816472936499,
        "command_count": 2,
        "settings": {},
        "on_pinged": {
            "title": null,
            "description": null,
            "color": null
        },
        "webhooks": {}
    },
    {
        "user_id": 777671599489810432,
        "command_count": 3,
        "settings": {},
        "on_pinged": {
            "title": null,
            "description": null,
            "color": null
        },
        "webhooks": {}
    },
    {
        "user_id": 797797679136374815,
        "command_count": 44,
        "settings": {},
        "on_pinged": {
            "title": "STFU!",
            "description": "Don't ping me right now",
            "color": 255
        },
        "webhooks": {}
    },
    {
        "user_id": 699692015172059256,
        "command_count": 6,
        "settings": {},
        "on_pinged": {
            "title": null,
            "description": null,
            "color": null
        },
        "webhooks": {}
    },
    {
        "user_id": 920880961955176540,
        "command_count": 44,
        "settings": {},
        "on_pinged": {
            "title": null,
            "description": null,
            "color": null
        },
        "webhooks": {}
    },
    {
        "user_id": 838024815368994826,
        "command_count": 4,
        "settings": {},
        "on_pinged": {
            "title": null,
            "description": null,
            "color": null
        },
        "webhooks": {}
    },
    {
        "user_id": 887024920096296962,
        "command_count": 18,
        "settings": {},
        "on_pinged": {
            "title": null,
            "description": null,
            "color": null
        },
        "webhooks": {}
    },
    {
        "user_id": 883740223115255839,
        "command_count": 3,
        "settings": {},
        "on_pinged": {
            "title": null,
            "description": null,
            "color": null
        },
        "webhooks": {}
    },
    {
        "user_id": 922535832554971237,
        "command_count": 18,
        "settings": {},
        "on_pinged": {
            "title": null,
            "description": null,
            "color": null
        },
        "webhooks": {}
    },
    {
        "user_id": 845905852053454889,
        "command_count": 29,
        "settings": {},
        "on_pinged": {
            "title": null,
            "description": null,
            "color": null
        },
        "webhooks": {}
    },
    {
        "user_id": 870876545764433980,
        "command_count": 21,
        "settings": {},
        "on_pinged": {
            "title": "What Do You Want \u4e42\u0e3f\u00d8\u2c6b\u00d8\u4e42",
            "description": "What Do You Need (why ping?)",
            "color": 0
        },
        "webhooks": {}
    },
    {
        "user_id": 835824068384129045,
        "command_count": 162,
        "settings": {},
        "on_pinged": {
            "title": "Hello",
            "description": "I probaly can't talk rn",
            "color": 16776960
        },
        "webhooks": {}
    },
    {
        "user_id": 928523288580329502,
        "command_count": 4,
        "settings": {},
        "on_pinged": {
            "title": null,
            "description": null,
            "color": null
        },
        "webhooks": {}
    },
    {
        "user_id": 590754348074663983,
        "command_count": 41,
        "settings": {},
        "on_pinged": {
            "title": null,
            "description": null,
            "color": null
        },
        "webhooks": {}
    },
    {
        "user_id": 841945331482230805,
        "command_count": 122,
        "settings": {},
        "on_pinged": {
            "title": "HI",
            "description": "be quiet and don't ping me again",
            "color": 16711680
        },
        "webhooks": {}
    },
    {
        "user_id": 507939895197827072,
        "command_count": 1,
        "settings": {},
        "on_pinged": {
            "title": null,
            "description": null,
            "color": null
        },
        "webhooks": {}
    },
    {
        "user_id": 557628352828014614,
        "command_count": 20,
        "settings": {},
        "on_pinged": {
            "title": null,
            "description": null,
            "color": null
        },
        "webhooks": {}
    },
    {
        "user_id": 458276816071950337,
        "command_count": 3,
        "settings": {},
        "on_pinged": {
            "title": null,
            "description": null,
            "color": null
        },
        "webhooks": {}
    },
    {
        "user_id": 905490795640016906,
        "command_count": 8,
        "settings": {},
        "on_pinged": {
            "title": "Shut up",
            "description": "Nerd",
            "color": 16711680
        },
        "webhooks": {}
    },
    {
        "user_id": 770854599224590366,
        "command_count": 1,
        "settings": {},
        "on_pinged": {
            "title": null,
            "description": null,
            "color": null
        },
        "webhooks": {}
    },
    {
        "user_id": 751205580550701058,
        "command_count": 1,
        "settings": {},
        "on_pinged": {
            "title": null,
            "description": null,
            "color": null
        },
        "webhooks": {}
    },
    {
        "user_id": 928038506285109289,
        "command_count": 18,
        "settings": {},
        "on_pinged": {
            "title": null,
            "description": null,
            "color": null
        },
        "webhooks": {}
    },
    {
        "user_id": 684667858244206592,
        "command_count": 38,
        "settings": {},
        "on_pinged": {
            "title": null,
            "description": null,
            "color": null
        },
        "webhooks": {}
    },
    {
        "user_id": 930997787754135564,
        "command_count": 7,
        "settings": {},
        "on_pinged": {
            "title": null,
            "description": null,
            "color": null
        },
        "webhooks": {}
    },
    {
        "user_id": 294882584201003009,
        "command_count": 35,
        "settings": {},
        "on_pinged": {
            "title": null,
            "description": null,
            "color": null
        },
        "webhooks": {}
    },
    {
        "user_id": 742788951546265621,
        "command_count": 1,
        "settings": {},
        "on_pinged": {
            "title": null,
            "description": null,
            "color": null
        },
        "webhooks": {}
    },
    {
        "user_id": 842668205025525810,
        "command_count": 1,
        "settings": {},
        "on_pinged": {
            "title": null,
            "description": null,
            "color": null
        },
        "webhooks": {}
    },
    {
        "user_id": 763530972142501948,
        "command_count": 1,
        "settings": {},
        "on_pinged": {
            "title": null,
            "description": null,
            "color": null
        },
        "webhooks": {}
    },
    {
        "user_id": 722503581722345492,
        "command_count": 7,
        "settings": {},
        "on_pinged": {
            "title": null,
            "description": null,
            "color": null
        },
        "webhooks": {}
    },
    {
        "user_id": 840869869843251241,
        "command_count": 1,
        "settings": {},
        "on_pinged": {
            "title": null,
            "description": null,
            "color": null
        },
        "webhooks": {}
    },
    {
        "user_id": 681081949594320929,
        "command_count": 12,
        "settings": {},
        "on_pinged": {
            "title": null,
            "description": null,
            "color": null
        },
        "webhooks": {}
    },
    {
        "user_id": 809769116876537856,
        "command_count": 70,
        "settings": {},
        "on_pinged": {
            "title": "STOP PINGING ME",
            "description": "ITS MAKE MY RINGTONE ANNOYING AND IF U KEEP PING ME ILL MAKE SURE I CRUSHED U IN A 1V1",
            "color": 16711680
        },
        "webhooks": {}
    },
    {
        "user_id": 901676058363977729,
        "command_count": 1,
        "settings": {},
        "on_pinged": {
            "title": null,
            "description": null,
            "color": null
        },
        "webhooks": {}
    },
    {
        "user_id": 821002499036282901,
        "command_count": 38,
        "settings": {},
        "on_pinged": {
            "title": null,
            "description": null,
            "color": null
        },
        "webhooks": {}
    },
    {
        "user_id": 893442943443161088,
        "command_count": 5,
        "settings": {},
        "on_pinged": {
            "title": null,
            "description": null,
            "color": null
        },
        "webhooks": {}
    },
    {
        "user_id": 897154056936636449,
        "command_count": 4,
        "settings": {},
        "on_pinged": {
            "title": null,
            "description": null,
            "color": null
        },
        "webhooks": {}
    },
    {
        "user_id": 843373957314641970,
        "command_count": 232,
        "settings": {},
        "on_pinged": {
            "title": null,
            "description": null,
            "color": null
        },
        "webhooks": {}
    },
    {
        "user_id": 876804245112913920,
        "command_count": 161,
        "settings": {},
        "on_pinged": {
            "title": null,
            "description": null,
            "color": null
        },
        "webhooks": {}
    },
    {
        "user_id": 903161406281646101,
        "command_count": 69,
        "settings": {},
        "on_pinged": {
            "title": null,
            "description": null,
            "color": null
        },
        "webhooks": {}
    },
    {
        "user_id": 860524146354421800,
        "command_count": 84,
        "settings": {},
        "on_pinged": {
            "title": null,
            "description": null,
            "color": null
        },
        "webhooks": {}
    },
    {
        "user_id": 751010533724913694,
        "command_count": 16,
        "settings": {},
        "on_pinged": {
            "title": null,
            "description": null,
            "color": null
        },
        "webhooks": {}
    },
    {
        "user_id": 716390085896962058,
        "command_count": 112,
        "settings": {},
        "on_pinged": {
            "title": null,
            "description": null,
            "color": null
        },
        "webhooks": {}
    },
    {
        "user_id": 740648197403443352,
        "command_count": 19,
        "settings": {},
        "on_pinged": {
            "title": null,
            "description": null,
            "color": null
        },
        "webhooks": {}
    },
    {
        "user_id": 767991071862423582,
        "command_count": 148,
        "settings": {},
        "on_pinged": {
            "title": "im angry \u2764\ufe0f",
            "description": "<@767991071862423582>",
            "color": 16761035
        },
        "webhooks": {}
    },
    {
        "user_id": 862258920038989845,
        "command_count": 156,
        "settings": {},
        "on_pinged": {
            "title": null,
            "description": null,
            "color": null
        },
        "webhooks": {}
    },
    {
        "user_id": 720341384518697072,
        "command_count": 1,
        "settings": {},
        "on_pinged": {
            "title": null,
            "description": null,
            "color": null
        },
        "webhooks": {}
    },
    {
        "user_id": 900365802895708172,
        "command_count": 113,
        "settings": {},
        "on_pinged": {
            "title": null,
            "description": null,
            "color": null
        },
        "webhooks": {}
    },
    {
        "user_id": 870176893515730994,
        "command_count": 3,
        "settings": {},
        "on_pinged": {
            "title": null,
            "description": null,
            "color": null
        },
        "webhooks": {}
    },
    {
        "user_id": 927196011355586592,
        "command_count": 3,
        "settings": {},
        "on_pinged": {
            "title": null,
            "description": null,
            "color": null
        },
        "webhooks": {}
    },
    {
        "user_id": 876048116179152936,
        "command_count": 67,
        "settings": {},
        "on_pinged": {
            "title": null,
            "description": null,
            "color": null
        },
        "webhooks": {}
    },
    {
        "user_id": 833971207249461359,
        "command_count": 1,
        "settings": {},
        "on_pinged": {
            "title": null,
            "description": null,
            "color": null
        },
        "webhooks": {}
    },
    {
        "user_id": 235148962103951360,
        "command_count": 39,
        "settings": {},
        "on_pinged": {
            "title": null,
            "description": null,
            "color": null
        },
        "webhooks": {}
    },
    {
        "user_id": 408785106942164992,
        "command_count": 105,
        "settings": {},
        "on_pinged": {
            "title": null,
            "description": null,
            "color": null
        },
        "webhooks": {}
    },
    {
        "user_id": 769615220674789397,
        "command_count": 3,
        "settings": {},
        "on_pinged": {
            "title": null,
            "description": null,
            "color": null
        },
        "webhooks": {}
    },
    {
        "user_id": 886979534396723332,
        "command_count": 18,
        "settings": {},
        "on_pinged": {
            "title": null,
            "description": null,
            "color": null
        },
        "webhooks": {}
    },
    {
        "user_id": 926215264201224192,
        "command_count": 1,
        "settings": {},
        "on_pinged": {
            "title": null,
            "description": null,
            "color": null
        },
        "webhooks": {}
    },
    {
        "user_id": 848156315670282250,
        "command_count": 4,
        "settings": {},
        "on_pinged": {
            "title": null,
            "description": null,
            "color": null
        },
        "webhooks": {}
    },
    {
        "user_id": 930763084593758249,
        "command_count": 1,
        "settings": {},
        "on_pinged": {
            "title": null,
            "description": null,
            "color": null
        },
        "webhooks": {}
    },
    {
        "user_id": 915105467896823868,
        "command_count": 6,
        "settings": {},
        "on_pinged": {
            "title": null,
            "description": null,
            "color": null
        },
        "webhooks": {}
    },
    {
        "user_id": 815926354766856212,
        "command_count": 4,
        "settings": {},
        "on_pinged": {
            "title": null,
            "description": null,
            "color": null
        },
        "webhooks": {}
    },
    {
        "user_id": 853875802197458964,
        "command_count": 1,
        "settings": {},
        "on_pinged": {
            "title": null,
            "description": null,
            "color": null
        },
        "webhooks": {}
    },
    {
        "user_id": 800441420531630111,
        "command_count": 30,
        "settings": {},
        "on_pinged": {
            "title": null,
            "description": null,
            "color": null
        },
        "webhooks": {}
    },
    {
        "user_id": 847733500282535976,
        "command_count": 5,
        "settings": {},
        "on_pinged": {
            "title": null,
            "description": null,
            "color": null
        },
        "webhooks": {}
    },
    {
        "user_id": 902122304119652384,
        "command_count": 2,
        "settings": {},
        "on_pinged": {
            "title": null,
            "description": null,
            "color": null
        },
        "webhooks": {}
    },
    {
        "user_id": 826389145995444254,
        "command_count": 6,
        "settings": {},
        "on_pinged": {
            "title": null,
            "description": null,
            "color": null
        },
        "webhooks": {}
    },
    {
        "user_id": 729550843849736232,
        "command_count": 7,
        "settings": {},
        "on_pinged": {
            "title": null,
            "description": null,
            "color": null
        },
        "webhooks": {}
    },
    {
        "user_id": 710440145534320720,
        "command_count": 1,
        "settings": {},
        "on_pinged": {
            "title": null,
            "description": null,
            "color": null
        },
        "webhooks": {}
    },
    {
        "user_id": 720057358205845546,
        "command_count": 3,
        "settings": {},
        "on_pinged": {
            "title": null,
            "description": null,
            "color": null
        },
        "webhooks": {}
    },
    {
        "user_id": 895905641749676054,
        "command_count": 23,
        "settings": {},
        "on_pinged": {
            "title": null,
            "description": null,
            "color": null
        },
        "webhooks": {}
    },
    {
        "user_id": 924756635803603014,
        "command_count": 1,
        "settings": {},
        "on_pinged": {
            "title": null,
            "description": null,
            "color": null
        },
        "webhooks": {}
    },
    {
        "user_id": 929989562120405004,
        "command_count": 1,
        "settings": {},
        "on_pinged": {
            "title": null,
            "description": null,
            "color": null
        },
        "webhooks": {}
    },
    {
        "user_id": 624572769484668938,
        "command_count": 1,
        "settings": {},
        "on_pinged": {
            "title": null,
            "description": null,
            "color": null
        },
        "webhooks": {}
    },
    {
        "user_id": 927212407623942144,
        "command_count": 7,
        "settings": {},
        "on_pinged": {
            "title": null,
            "description": null,
            "color": null
        },
        "webhooks": {}
    },
    {
        "user_id": 843888781257342987,
        "command_count": 14,
        "settings": {},
        "on_pinged": {
            "title": null,
            "description": null,
            "color": null
        },
        "webhooks": {}
    },
    {
        "user_id": 438057969251254293,
        "command_count": 130,
        "settings": {},
        "on_pinged": {
            "title": null,
            "description": null,
            "color": null
        },
        "webhooks": {}
    },
    {
        "user_id": 857516478390599700,
        "command_count": 1,
        "settings": {},
        "on_pinged": {
            "title": null,
            "description": null,
            "color": null
        },
        "webhooks": {}
    },
    {
        "user_id": 795901445799018496,
        "command_count": 2,
        "settings": {},
        "on_pinged": {
            "title": null,
            "description": null,
            "color": null
        },
        "webhooks": {}
    },
    {
        "user_id": 477404830076502027,
        "command_count": 2,
        "settings": {},
        "on_pinged": {
            "title": null,
            "description": null,
            "color": null
        },
        "webhooks": {}
    },
    {
        "user_id": 794922182235914270,
        "command_count": 14,
        "settings": {},
        "on_pinged": {
            "title": null,
            "description": null,
            "color": null
        },
        "webhooks": {}
    },
    {
        "user_id": 428463277400391683,
        "command_count": 2,
        "settings": {},
        "on_pinged": {
            "title": null,
            "description": null,
            "color": null
        },
        "webhooks": {}
    },
    {
        "user_id": 705998279107936276,
        "command_count": 18,
        "settings": {},
        "on_pinged": {
            "title": null,
            "description": null,
            "color": null
        },
        "webhooks": {}
    },
    {
        "user_id": 842264878592426014,
        "command_count": 15,
        "settings": {},
        "on_pinged": {
            "title": null,
            "description": null,
            "color": null
        },
        "webhooks": {}
    },
    {
        "user_id": 908360161515687968,
        "command_count": 1,
        "settings": {},
        "on_pinged": {
            "title": null,
            "description": null,
            "color": null
        },
        "webhooks": {}
    },
    {
        "user_id": 827192816756588585,
        "command_count": 1,
        "settings": {},
        "on_pinged": {
            "title": null,
            "description": null,
            "color": null
        },
        "webhooks": {}
    },
    {
        "user_id": 753303928262623293,
        "command_count": 1,
        "settings": {},
        "on_pinged": {
            "title": null,
            "description": null,
            "color": null
        },
        "webhooks": {}
    },
    {
        "user_id": 481377376475938826,
        "command_count": 110,
        "settings": {},
        "on_pinged": {
            "title": null,
            "description": "Sub to Michael media group",
            "color": 255
        },
        "webhooks": {}
    },
    {
        "user_id": 774510369489158154,
        "command_count": 5,
        "settings": {},
        "on_pinged": {
            "title": null,
            "description": null,
            "color": null
        },
        "webhooks": {}
    },
    {
        "user_id": 807926574443266049,
        "command_count": 3,
        "settings": {},
        "on_pinged": {
            "title": null,
            "description": null,
            "color": null
        },
        "webhooks": {}
    },
    {
        "user_id": 792608802901983232,
        "command_count": 2,
        "settings": {},
        "on_pinged": {
            "title": null,
            "description": null,
            "color": null
        },
        "webhooks": {}
    },
    {
        "user_id": 550278380243648513,
        "command_count": 53,
        "settings": {},
        "on_pinged": {
            "title": null,
            "description": null,
            "color": null
        },
        "webhooks": {}
    },
    {
        "user_id": 390668810073538560,
        "command_count": 16,
        "settings": {},
        "on_pinged": {
            "title": null,
            "description": null,
            "color": null
        },
        "webhooks": {}
    },
    {
        "user_id": 851960190587633664,
        "command_count": 2,
        "settings": {},
        "on_pinged": {
            "title": null,
            "description": null,
            "color": null
        },
        "webhooks": {}
    },
    {
        "user_id": 818200812030787635,
        "command_count": 6,
        "settings": {},
        "on_pinged": {
            "title": null,
            "description": null,
            "color": null
        },
        "webhooks": {}
    },
    {
        "user_id": 793834479722037261,
        "command_count": 1,
        "settings": {},
        "on_pinged": {
            "title": null,
            "description": null,
            "color": null
        },
        "webhooks": {}
    },
    {
        "user_id": 924810896839176192,
        "command_count": 1,
        "settings": {},
        "on_pinged": {
            "title": null,
            "description": null,
            "color": null
        },
        "webhooks": {}
    },
    {
        "user_id": 770933336620400650,
        "command_count": 2,
        "settings": {},
        "on_pinged": {
            "title": null,
            "description": null,
            "color": null
        },
        "webhooks": {}
    },
    {
        "user_id": 698233602319712257,
        "command_count": 9,
        "settings": {},
        "on_pinged": {
            "title": null,
            "description": null,
            "color": null
        }
    },
    {
        "user_id": 935337927976812594,
        "command_count": 2,
        "settings": {},
        "on_pinged": {
            "title": null,
            "description": null,
            "color": null
        }
    },
    {
        "user_id": 488212137207136295,
        "command_count": 2,
        "settings": {},
        "on_pinged": {
            "title": null,
            "description": null,
            "color": null
        }
    },
    {
        "user_id": 818001830369820724,
        "command_count": 1,
        "settings": {},
        "on_pinged": {
            "title": null,
            "description": null,
            "color": null
        }
    },
    {
        "user_id": 818494318955462677,
        "command_count": 1,
        "settings": {},
        "on_pinged": {
            "title": null,
            "description": null,
            "color": null
        }
    },
    {
        "user_id": 882806101949702165,
        "command_count": 2,
        "settings": {},
        "on_pinged": {
            "title": null,
            "description": null,
            "color": null
        }
    },
    {
        "user_id": 803168096662847520,
        "command_count": 4,
        "settings": {},
        "on_pinged": {
            "title": null,
            "description": null,
            "color": null
        }
    },
    {
        "user_id": 762678334966202430,
        "command_count": 1,
        "settings": {},
        "on_pinged": {
            "title": null,
            "description": null,
            "color": null
        }
    },
    {
        "user_id": 573730474577625098,
        "command_count": 2,
        "settings": {},
        "on_pinged": {
            "title": null,
            "description": null,
            "color": null
        }
    },
    {
        "user_id": 818043965700833281,
        "command_count": 1,
        "settings": {},
        "on_pinged": {
            "title": null,
            "description": null,
            "color": null
        }
    },
    {
        "user_id": 911803872698318919,
        "command_count": 1,
        "settings": {},
        "on_pinged": {
            "title": null,
            "description": null,
            "color": null
        }
    },
    {
        "user_id": 698728199923826709,
        "command_count": 9,
        "settings": {},
        "on_pinged": {
            "title": null,
            "description": null,
            "color": null
        }
    },
    {
        "user_id": 896109009369694208,
        "command_count": 1,
        "settings": {},
        "on_pinged": {
            "title": null,
            "description": null,
            "color": null
        }
    },
    {
        "user_id": 913027393696968744,
        "command_count": 4,
        "settings": {},
        "on_pinged": {
            "title": "Stop",
            "description": "Stop",
            "color": 16711680
        }
    },
    {
        "user_id": 867831015262388294,
        "command_count": 8,
        "settings": {},
        "on_pinged": {
            "title": null,
            "description": null,
            "color": null
        }
    },
    {
        "user_id": 787584393463201802,
        "command_count": 1,
        "settings": {},
        "on_pinged": {
            "title": null,
            "description": null,
            "color": null
        }
    },
    {
        "user_id": 813435196040544297,
        "command_count": 1,
        "settings": {},
        "on_pinged": {
            "title": null,
            "description": null,
            "color": null
        }
    },
    {
        "user_id": 767420223539511369,
        "command_count": 1,
        "settings": {},
        "on_pinged": {
            "title": null,
            "description": null,
            "color": null
        }
    },
    {
        "user_id": 882485034555166770,
        "command_count": 2,
        "settings": {},
        "on_pinged": {
            "title": null,
            "description": null,
            "color": null
        }
    },
    {
        "user_id": 654066248249901066,
        "command_count": 1,
        "settings": {},
        "on_pinged": {
            "title": null,
            "description": null,
            "color": null
        }
    },
    {
        "user_id": 849285016064098344,
        "command_count": 1,
        "settings": {},
        "on_pinged": {
            "title": null,
            "description": null,
            "color": null
        }
    }
]